pytorchltr/__init__.py
pytorchltr/utils/tensor_operations.py
pytorchltr/utils/file.py
pytorchltr/utils/downloader.py
pytorchltr/utils/__init__.py
pytorchltr/utils/progress.py
pytorchltr/datasets/__init__.py
pytorchltr/datasets/list_sampler.py
pytorchltr/datasets/svmrank/mslr30k.py
pytorchltr/datasets/svmrank/mslr10k.py
pytorchltr/datasets/svmrank/example3.py
pytorchltr/datasets/svmrank/istella.py
pytorchltr/datasets/svmrank/svmrank.py
pytorchltr/datasets/svmrank/istella_x.py
pytorchltr/datasets/svmrank/istella_s.py
pytorchltr/datasets/svmrank/__init__.py
pytorchltr/datasets/svmrank/parser/svmrank_parser.cpython-37m-x86_64-linux-gnu.so
pytorchltr/datasets/svmrank/parser/__init__.py
pytorchltr/click_simulation/pbm.py
pytorchltr/click_simulation/__init__.py
pytorchltr/evaluation/arp.py
pytorchltr/evaluation/trec.py
pytorchltr/evaluation/dcg.py
pytorchltr/evaluation/__init__.py
pytorchltr/loss/pairwise_lambda.py
pytorchltr/loss/pairwise_additive.py
pytorchltr/loss/__init__.py
pytorchltr-0.2.1.dist-info/LICENSE.md
pytorchltr-0.2.1.dist-info/WHEEL
pytorchltr-0.2.1.dist-info/top_level.txt
pytorchltr-0.2.1.dist-info/RECORD
pytorchltr-0.2.1.dist-info/METADATA
