Metadata-Version: 2.1
Name: pytorchltr
Version: 0.2.1
Summary: Learning to Rank with PyTorch
Home-page: https://github.com/rjagerman/pytorchltr
Author: Rolf Jagerman
Author-email: rjagerman@gmail.com
License: MIT
Platform: UNKNOWN
Classifier: Programming Language :: Python :: 3
Classifier: License :: OSI Approved :: MIT License
Classifier: Operating System :: OS Independent
Requires-Python: >=3.5
